alibabacloud_privatelink20200415/__init__.py
alibabacloud_privatelink20200415/client.py
alibabacloud_privatelink20200415/models/__init__.py
alibabacloud_privatelink20200415/models/_add_user_to_vpc_endpoint_service_request.py
alibabacloud_privatelink20200415/models/_add_user_to_vpc_endpoint_service_response.py
alibabacloud_privatelink20200415/models/_add_user_to_vpc_endpoint_service_response_body.py
alibabacloud_privatelink20200415/models/_add_zone_to_vpc_endpoint_request.py
alibabacloud_privatelink20200415/models/_add_zone_to_vpc_endpoint_response.py
alibabacloud_privatelink20200415/models/_add_zone_to_vpc_endpoint_response_body.py
alibabacloud_privatelink20200415/models/_attach_resource_to_vpc_endpoint_service_request.py
alibabacloud_privatelink20200415/models/_attach_resource_to_vpc_endpoint_service_response.py
alibabacloud_privatelink20200415/models/_attach_resource_to_vpc_endpoint_service_response_body.py
alibabacloud_privatelink20200415/models/_attach_security_group_to_vpc_endpoint_request.py
alibabacloud_privatelink20200415/models/_attach_security_group_to_vpc_endpoint_response.py
alibabacloud_privatelink20200415/models/_attach_security_group_to_vpc_endpoint_response_body.py
alibabacloud_privatelink20200415/models/_change_resource_group_request.py
alibabacloud_privatelink20200415/models/_change_resource_group_response.py
alibabacloud_privatelink20200415/models/_change_resource_group_response_body.py
alibabacloud_privatelink20200415/models/_check_product_open_response.py
alibabacloud_privatelink20200415/models/_check_product_open_response_body.py
alibabacloud_privatelink20200415/models/_create_vpc_endpoint_request.py
alibabacloud_privatelink20200415/models/_create_vpc_endpoint_response.py
alibabacloud_privatelink20200415/models/_create_vpc_endpoint_response_body.py
alibabacloud_privatelink20200415/models/_create_vpc_endpoint_service_request.py
alibabacloud_privatelink20200415/models/_create_vpc_endpoint_service_response.py
alibabacloud_privatelink20200415-4.0.6.dist-info/LICENSE
alibabacloud_privatelink20200415-4.0.6.dist-info/METADATA
alibabacloud_privatelink20200415-4.0.6.dist-info/WHEEL
alibabacloud_privatelink20200415-4.0.6.dist-info/top_level.txt
alibabacloud_privatelink20200415-4.0.6.dist-info/RECORD
